webimage/__init__.py
webimage/_scribe.py
webimage/_transformations.py
webimage/_typing.py
webimage/_webimage.py
webimage/properties.py
webimage-0.3.0.dist-info/WHEEL
webimage-0.3.0.dist-info/METADATA
webimage-0.3.0.dist-info/RECORD
