Metadata-Version: 2.3
Name: webimage
Version: 0.3.0
Summary: Webify your images
Keywords: images,web
Author: Mario Munoz
Author-email: Mario Munoz <pythonbynight@gmail.com>
Classifier: Development Status :: 3 - Alpha
Classifier: Intended Audience :: Developers
Classifier: Natural Language :: English
Classifier: Operating System :: OS Independent
Classifier: Programming Language :: Python :: 3
Classifier: Programming Language :: Python :: 3.14
Classifier: Topic :: Software Development
Classifier: Typing :: Typed
Requires-Dist: attrs>=25.4.0
Requires-Dist: pillow>=12.0.0
Requires-Python: >=3.14
Project-URL: Changelog, https://codeberg.org/pythonbynight/webimage/releases
Project-URL: Homepage, https://codeberg.org/pythonbynight/webimage
Project-URL: Issue, https://codeberg.org/pythonbynight/webimage/issues
Project-URL: Source, https://codeberg.org/pythonbynight/webimage
